.travis.yml
AUTHOR.txt
CHANGES.rst
COPYRIGHT.txt
LICENSE.txt
MANIFEST.in
README.rst
bootstrap.py
buildout.cfg
setup.py
tox.ini
src/z3c/__init__.py
src/z3c.datagenerator.egg-info/PKG-INFO
src/z3c.datagenerator.egg-info/SOURCES.txt
src/z3c.datagenerator.egg-info/dependency_links.txt
src/z3c.datagenerator.egg-info/namespace_packages.txt
src/z3c.datagenerator.egg-info/not-zip-safe
src/z3c.datagenerator.egg-info/requires.txt
src/z3c.datagenerator.egg-info/top_level.txt
src/z3c/datagenerator/README.rst
src/z3c/datagenerator/README3.rst
src/z3c/datagenerator/__init__.py
src/z3c/datagenerator/ccTLD.csv
src/z3c/datagenerator/demographics.py
src/z3c/datagenerator/firstnames.txt
src/z3c/datagenerator/gTLD.csv
src/z3c/datagenerator/generator.py
src/z3c/datagenerator/interfaces.py
src/z3c/datagenerator/lastnames.txt
src/z3c/datagenerator/net.py
src/z3c/datagenerator/tests.py
src/z3c/datagenerator/us-cities.txt
src/z3c/datagenerator/us-states.txt
src/z3c/datagenerator/us-street-names.txt
src/z3c/datagenerator/us-street-postfix.txt
src/z3c/datagenerator/words.txt