Metadata-Version: 1.1
Name: z3c.datagenerator
Version: 2.1.1
Summary: Datagenerator for Testing and Sample Data
Home-page: http://pypi.python.org/pypi/z3c.datagenerator
Author: Stephan Richter and the Zope Community
Author-email: zope3-dev@zope.org
License: ZPL 2.1
Keywords: data generator sampledata
Platform: UNKNOWN
Classifier: Development Status :: 5 - Production/Stable
Classifier: Intended Audience :: Developers
Classifier: License :: OSI Approved :: Zope Public License
Classifier: Natural Language :: English
Classifier: Operating System :: OS Independent
Classifier: Programming Language :: Python
Classifier: Programming Language :: Python :: 2
Classifier: Programming Language :: Python :: 2.6
Classifier: Programming Language :: Python :: 2.7
Classifier: Programming Language :: Python :: 3
Classifier: Programming Language :: Python :: 3.3
Classifier: Programming Language :: Python :: Implementation :: CPython
Classifier: Programming Language :: Python :: Implementation :: PyPy
Classifier: Topic :: Software Development :: Libraries :: Python Modules
Classifier: Topic :: Utilities
